kfp_components/__init__.py
kfp_components/components/__init__.py
kfp_components/components/data_processing/__init__.py
kfp_components/components/deployment/__init__.py
kfp_components/components/evaluation/__init__.py
kfp_components/components/training/__init__.py
kfp_components/pipelines/__init__.py
kfp_components/pipelines/data_processing/__init__.py
kfp_components/pipelines/deployment/__init__.py
kfp_components/pipelines/evaluation/__init__.py
kfp_components/pipelines/training/__init__.py
kfp_components-0.0.1.dist-info/licenses/LICENSE
kfp_components-0.0.1.dist-info/METADATA
kfp_components-0.0.1.dist-info/WHEEL
kfp_components-0.0.1.dist-info/top_level.txt
kfp_components-0.0.1.dist-info/RECORD
