Metadata-Version: 2.4
Name: kfp-components
Version: 0.0.1
Summary: A collection of reusable components and pipelines for Kubeflow Pipelines
Author: Kubeflow Community
License-Expression: Apache-2.0
Project-URL: Homepage, https://www.kubeflow.org/docs/components/pipelines/
Project-URL: Documentation, https://github.com/kubeflow/pipelines-components/tree/main/docs
Project-URL: Repository, https://github.com/kubeflow/pipelines-components
Project-URL: Issues, https://github.com/kubeflow/pipelines-components/issues
Requires-Python: >=3.11
License-File: LICENSE
Requires-Dist: kfp>=2.15.0
Provides-Extra: ci
Requires-Dist: pyyaml; extra == "ci"
Requires-Dist: pytest; extra == "ci"
Requires-Dist: docstring-parser; extra == "ci"
Requires-Dist: jinja2; extra == "ci"
Provides-Extra: dev
Requires-Dist: kfp-components[ci]; extra == "dev"
Dynamic: license-file
